{
  "pageData": {
    "header": {
      "hugeNumber": "2",
      "mainTitle": "植保无人机安全作业"
    },
    "introParagraph": "对于植保无人机如何实现安全作业的问题，首先要知道植保无人机进行作业的基本流程，在前期准备阶段、作业实施阶段、作业结束阶段需要注意的问题，应该满足哪些相关规定，如何应对紧急情况的发生，以上都是本节讲述的内容。",
    "drones": [
      {
        "iconClass": "fa-solid fa-screwdriver-wrench",
        "title": "作业流程",
        "description": "植保无人机作业前期需准备：准备设备、组织人员、确定飞防任务与喷洒药物、测绘地块，还需注意作业时间的天气情况。",
        "features": [
          {
            "label": "前期准备阶段",
            "text": "植保无人机作业前期需准备：准备设备、组织人员、确定飞防任务与喷洒药物、测绘地块，还需注意作业时间的天气情况。"
          },
          {
            "label": "准备设备",
            "text": "准备好植保无人机，并做前期检查。多组电池充满电，并准备好车载充电设备。"
          },
          {
            "label": "组织人员",
            "text": "飞防作业前，联系并准备好操作员，确定操作员、时间、地点。"
          },
          {
            "label": "确定飞防任务与喷洒药物",
            "text": "明确飞防任务内容，做好预防与安全准备。"
          },
          {
            "label": "测绘地块",
            "text": "最好提前勘探或测绘好飞防作业地块，观察地形与障碍物，判断作业难度与飞行风险。提前测绘，规避障碍物。"
          },
          {
            "label": "天气情况",
            "text": "提前关注作业时间的天气状况，规避大风、雨、雪等不利作业的天气。"
          },
          {
            "label": "作业实施阶段",
            "text": "植保无人机作业实施阶段，多数情况是植保无人机规划航线并设置参数后自主飞行作业。作业期间，操作员应时刻关注无人机电量与药量变化，重复更换电池与添加药液的过程。"
          },
          {
            "label": "作业结束阶段",
            "text": "作业结束后，对无人机设备进行检查及清洗。对植保无人机系统进行检查、检查各项物资消耗（农药、电池等），记录当天作业亩数和飞行架次、当日用药量与总作业亩数是否吻合等，在地面站软件上传日志，并为后续作业做好准备。"
          }
        ],
        "imageUrl": "images/c0402-001@2x.6b021b99.jpg"
      },
      {
        "iconClass": "fa-solid fa-shield-halved",
        "title": "作业安全规则",
        "description": "植保无人机作为一个新兴的空中应用平台，其系统复杂、关联性高、应用环境多变等特点要求操作员必须具备较高的技术水平，在作业过程中时刻牢记“安全第一、预防为主”的方针，使植保作业工作“有序、可靠、高效”开展。",
        "features": [
          {
            "label": "人员安全规则",
            "text": "（1）人员资格要求：植保无人机操作员须持有民航局植保无人机驾驶员电子执照和植保无人机驾驶员培训合格证（图4.2.2）。 （2）人员操控能力要求：操作员必须通过专业的理论培训与实际操作训练，掌握并具备植保无人机安装、手动操控、自动飞行以及安全作业和应急处置的综合能力。"
          },
          {
            "label": "人员资格要求",
            "text": "植保无人机操作员须持有民航局植保无人机驾驶员电子执照和植保无人机驾驶员培训合格证（图4.2.2）。"
          },
          {
            "label": "人员操控能力要求",
            "text": "操作员必须通过专业的理论培训与实际操作训练，掌握并具备植保无人机安装、手动操控、自动飞行以及安全作业和应急处置的综合能力。"
          },
          {
            "label": "其他要求",
            "text": "对操作员的年龄、身体状况、药品知识掌握情况及施药技能等的要求。"
          },
          {
            "label": "设备安全规则",
            "text": "（1）设备实名登记：植保无人机在使用前须完成民航系统实名登记（图4.2.3）。 （2）重要性能指标：电池、桨叶、机架系统、通信链路达到飞行时的参数要求。"
          },
          {
            "label": "设备实名登记",
            "text": "植保无人机在使用前须完成民航系统实名登记（图4.2.3）。"
          },
          {
            "label": "重要性能指标",
            "text": "电池、桨叶、机架系统、通信链路达到飞行时的参数要求。操控设备应具有显示植保无人机的实时位置、高度、速度等信息的仪器仪表。"
          },
          {
            "label": "设备保险",
            "text": "机身险保障无人机意外事故的维修与换新费用；第三者责任险保障意外原因造成的第三者损失。"
          },
          {
            "label": "环境安全规则",
            "text": "（1）地面因素：地形地貌和障碍物，对植保无人机安全飞行有一定的影响。 （2）磁罗盘与卫星信号：植保无人机跨区域作业，需要对无人机的磁罗盘进行校准。"
          },
          {
            "label": "地面因素",
            "text": "地形地貌和障碍物，对植保无人机安全飞行有一定的影响。"
          },
          {
            "label": "磁罗盘与卫星信号",
            "text": "植保无人机跨区域作业，需要对无人机的磁罗盘进行校准。磁罗盘工作要远离强大磁场区，如大块金属、铁质栅栏、磁铁矿脉、高压电等。"
          },
          {
            "label": "周边环境",
            "text": "作业区及周边10m范围内应避免有电线杆、树木及建筑物等影响植保无人机作业的障碍物；作业区应远离养殖场、学校、医院及居民生活区，远离水源地、牧草地等其他生态敏感区等。"
          },
          {
            "label": "天气因素",
            "text": "雾霾、风、温度、湿度及其他恶劣天气都影响着植保无人机作业飞行。雾霾影响作业能见度，能见度越低，安全隐患越大；"
          },
          {
            "label": "飞行安全规则",
            "text": "* 禁飞区不飞。 * 无驾驶员合格证者不飞。"
          },
          {
            "label": "禁止飞行原则（五不飞）",
            "text": "（1）禁止飞行原则（五不飞）。 * 禁飞区不飞。"
          },
          {
            "label": "飞行作业前安全准备（六项准备）",
            "text": "（2）飞行作业前安全准备（六项准备）。 * 时间安排，避免在高温天气下中午连续作业，否则不仅药效不佳，而且容易中暑。"
          },
          {
            "label": "飞行操作注意事项",
            "text": "（3）飞行操作注意事项。 * 飞行高度要求，禁止超高空飞行（植保无人机飞行高度禁止超过地面30m）。"
          }
        ],
        "imageUrl": "images/c0402-002@2x.780ca711.jpg"
      },
      {
        "iconClass": "fa-solid fa-book-open",
        "title": "作业应急情况处理",
        "description": "植保无人机作业过程中，时间久了，难免会发生一些紧急突发情况。作业中应有防止机械碰伤、划伤、砸伤的保护，发现异常及时处理，处理不了及时上报。",
        "features": [
          {
            "label": "施药人员出现头疼、头昏、恶心、呕吐等症状时，应立即离开施药现场，脱掉污染的衣裤，及时携带农药标签到医院治疗",
            "text": "（1）施药人员出现头疼、头昏、恶心、呕吐等症状时，应立即离开施药现场，脱掉污染的衣裤，及时携带农药标签到医院治疗。"
          },
          {
            "label": "拨打当地疾病预防控制中心或中毒急救中心电话",
            "text": "（2）拨打当地疾病预防控制中心或中毒急救中心电话。"
          }
        ]
      }
    ]
  }
}
